{
  "buildCommand" : {
    "command" : "prepareForIndexing",
    "enableIndexBuildArena" : false,
    "targets" : null
  },
  "configuredTargets" : [
    {
      "guid" : "7c6c03f366458675d5b20bb961d7de3900930efb1d726057465f0a9860b4a870"
    }
  ],
  "containerPath" : "/Users/u22152/Documents/GitHub/Light-is-Gone/LightIsGone/LightIsGone (Mac).xcworkspace",
  "continueBuildingAfterErrors" : true,
  "enableIndexBuildArena" : false,
  "hideShellScriptEnvironment" : false,
  "parameters" : {
    "action" : "build",
    "activeArchitecture" : "arm64",
    "activeRunDestination" : {
      "disableOnlyActiveArch" : false,
      "platform" : "macosx",
      "sdk" : "macosx14.2",
      "sdkVariant" : "macos",
      "supportedArchitectures" : [
        "arm64e",
        "arm64",
        "x86_64"
      ],
      "targetArchitecture" : "arm64"
    },
    "arenaInfo" : {
      "buildIntermediatesPath" : "",
      "buildProductsPath" : "",
      "derivedDataPath" : "/Users/u22152/Library/Developer/Xcode/DerivedData",
      "indexDataStoreFolderPath" : "/Users/u22152/Library/Developer/Xcode/DerivedData/LightIsGone_(Mac)-bnliymfxwzfeovdelwjereoxwacj/Index.noindex/DataStore",
      "indexEnableDataStore" : true,
      "indexPCHPath" : "/Users/u22152/Library/Developer/Xcode/DerivedData/LightIsGone_(Mac)-bnliymfxwzfeovdelwjereoxwacj/Index.noindex/PrecompiledHeaders",
      "pchPath" : ""
    },
    "configurationName" : "Development",
    "overrides" : {
      "synthesized" : {
        "table" : {
          "ENABLE_PREVIEWS" : "NO",
          "ENABLE_XOJIT_PREVIEWS" : "NO"
        }
      }
    }
  },
  "schemeCommand" : "launch",
  "showNonLoggedProgress" : true,
  "useDryRun" : false,
  "useImplicitDependencies" : true,
  "useLegacyBuildLocations" : false,
  "useParallelTargets" : true
}